gtasks_api/__init__.py
gtasks_api/gtasks_api.py
gtasks_api-0.0.8.dist-info/LICENSE
gtasks_api-0.0.8.dist-info/METADATA
gtasks_api-0.0.8.dist-info/WHEEL
gtasks_api-0.0.8.dist-info/top_level.txt
gtasks_api-0.0.8.dist-info/RECORD
