Metadata-Version: 2.1
Name: gtasks-api
Version: 0.0.8
Summary: Based on quickstart sample by Google
Home-page: https://github.com/BlueBlueBlob/gtasks_api
Author: BlueBlueBlob
Author-email: adrien.lesot@gmail.com
License: MIT
Keywords: google,tasks,task,gtasks,gtask
Platform: UNKNOWN
Requires-Dist: google-api-python-client
Requires-Dist: google-auth-httplib2
Requires-Dist: google-auth-oauthlib
